RegexRiot/__init__.py
RegexRiot/_basic_expressions.py
RegexRiot/_operations.py
RegexRiot/_riot.py
regexriot-0.0.4.dist-info/METADATA
regexriot-0.0.4.dist-info/WHEEL
regexriot-0.0.4.dist-info/licenses/LICENSE
regexriot-0.0.4.dist-info/RECORD
