Metadata-Version: 2.3
Name: RegexRiot
Version: 0.0.4
Summary: A simple easy to use and read regex maker.
Author-email: Rahul Kandekar <rahukand@gmail.com>
License-File: LICENSE
Classifier: License :: OSI Approved :: MIT License
Classifier: Operating System :: OS Independent
Classifier: Programming Language :: Python :: 3
Requires-Python: >=3.8
